MANIFEST.in
README.rst
buildout.cfg
requirements.txt
setup.py
version.txt
bob/__init__.py
bob.ip.pytorch_extractor.egg-info/PKG-INFO
bob.ip.pytorch_extractor.egg-info/SOURCES.txt
bob.ip.pytorch_extractor.egg-info/dependency_links.txt
bob.ip.pytorch_extractor.egg-info/entry_points.txt
bob.ip.pytorch_extractor.egg-info/not-zip-safe
bob.ip.pytorch_extractor.egg-info/requires.txt
bob.ip.pytorch_extractor.egg-info/top_level.txt
bob/ip/__init__.py
bob/ip/pytorch_extractor/CNN8.py
bob/ip/pytorch_extractor/CasiaNet.py
bob/ip/pytorch_extractor/__init__.py
bob/ip/pytorch_extractor/test.py
doc/conf.py
doc/guide.rst
doc/index.rst
doc/py_api.rst