Metadata-Version: 1.1
Name: bob.ip.pytorch-extractor
Version: 0.0.2
Summary: Extract features from images using (C)NN built with pyTorch
Home-page: https://gitlab.idiap.ch/heusch/bob.ip.pytorch_extractor
Author: Guillaume Heusch
Author-email: guillaume.heusch@idiap.ch
License: BSD
Keywords: pytorch
Platform: UNKNOWN
Classifier: Framework :: Bob
Classifier: Development Status :: 3 - Alpha
Classifier: Intended Audience :: Developers
Classifier: License :: OSI Approved :: BSD License
Classifier: Natural Language :: English
Classifier: Programming Language :: Python
Classifier: Topic :: Scientific/Engineering :: Artificial Intelligence
